{
"meta":{"test_sets":[],"test_metrics":[],"learn_metrics":[{"best_value":"Min","name":"Logloss"}],"launch_mode":"Train","parameters":"","iteration_count":1000,"learn_sets":["learn"],"name":"experiment"},
"iterations":[
{"learn":[0.6884338198],"iteration":0,"passed_time":0.03489824897,"remaining_time":34.86335072},
{"learn":[0.6855894563],"iteration":1,"passed_time":0.0654172471,"remaining_time":32.6432063},
{"learn":[0.6821423723],"iteration":2,"passed_time":0.09828385422,"remaining_time":32.66300088},
{"learn":[0.6783419742],"iteration":3,"passed_time":0.1280340412,"remaining_time":31.88047625},
{"learn":[0.6741107715],"iteration":4,"passed_time":0.1549862828,"remaining_time":30.84227028},
{"learn":[0.6703043693],"iteration":5,"passed_time":0.1844182324,"remaining_time":30.55195383},
{"learn":[0.6667784193],"iteration":6,"passed_time":0.2172412943,"remaining_time":30.81722932},
{"learn":[0.663372292],"iteration":7,"passed_time":0.235541484,"remaining_time":29.20714402},
{"learn":[0.6598849583],"iteration":8,"passed_time":0.2667977415,"remaining_time":29.37739576},
{"learn":[0.6561632258],"iteration":9,"passed_time":0.2967945422,"remaining_time":29.38265967},
{"learn":[0.6525769859],"iteration":10,"passed_time":0.3287215417,"remaining_time":29.55505498},
{"learn":[0.6493200255],"iteration":11,"passed_time":0.3563526742,"remaining_time":29.33970351},
{"learn":[0.6463912602],"iteration":12,"passed_time":0.3934926032,"remaining_time":29.87516918},
{"learn":[0.6436953197],"iteration":13,"passed_time":0.4170998272,"remaining_time":29.37574498},
{"learn":[0.6403909766],"iteration":14,"passed_time":0.4488848518,"remaining_time":29.47677194},
{"learn":[0.6376463303],"iteration":15,"passed_time":0.4801046941,"remaining_time":29.52643869},
{"learn":[0.6344752421],"iteration":16,"passed_time":0.5156066374,"remaining_time":29.81419556},
{"learn":[0.6321915372],"iteration":17,"passed_time":0.5427071898,"remaining_time":29.60769224},
{"learn":[0.6293861329],"iteration":18,"passed_time":0.5736687702,"remaining_time":29.6194244},
{"learn":[0.6260926231],"iteration":19,"passed_time":0.5979531996,"remaining_time":29.29970678},
{"learn":[0.6232538307],"iteration":20,"passed_time":0.6249420564,"remaining_time":29.13420349},
{"learn":[0.6202028184],"iteration":21,"passed_time":0.6497242706,"remaining_time":28.88319712},
{"learn":[0.6173999398],"iteration":22,"passed_time":0.6941293907,"remaining_time":29.48540934},
{"learn":[0.6137584599],"iteration":23,"passed_time":0.7295732409,"remaining_time":29.6693118},
{"learn":[0.6117234145],"iteration":24,"passed_time":0.7620546088,"remaining_time":29.72012974},
{"learn":[0.6081628912],"iteration":25,"passed_time":0.7930322767,"remaining_time":29.70820914},
{"learn":[0.605384111],"iteration":26,"passed_time":0.8243922983,"remaining_time":29.70865579},
{"learn":[0.6023076369],"iteration":27,"passed_time":0.8553280275,"remaining_time":29.69210153},
{"learn":[0.5991395814],"iteration":28,"passed_time":0.8834115448,"remaining_time":29.57905552},
{"learn":[0.5961260213],"iteration":29,"passed_time":0.9148976777,"remaining_time":29.58169158},
{"learn":[0.5933595634],"iteration":30,"passed_time":0.9482324374,"remaining_time":29.6399107},
{"learn":[0.5901389553],"iteration":31,"passed_time":0.9757012598,"remaining_time":29.51496311},
{"learn":[0.5870593909],"iteration":32,"passed_time":1.007843472,"remaining_time":29.5328678},
{"learn":[0.5840789412],"iteration":33,"passed_time":1.046962792,"remaining_time":29.7460605},
{"learn":[0.5813466295],"iteration":34,"passed_time":1.077126447,"remaining_time":29.69791491},
{"learn":[0.5785490188],"iteration":35,"passed_time":1.108597655,"remaining_time":29.68578165},
{"learn":[0.5762124178],"iteration":36,"passed_time":1.146998515,"remaining_time":29.85296135},
{"learn":[0.5734786994],"iteration":37,"passed_time":1.176726623,"remaining_time":29.78976344},
{"learn":[0.5711619828],"iteration":38,"passed_time":1.20949939,"remaining_time":29.80330547},
{"learn":[0.5683995708],"iteration":39,"passed_time":1.241327673,"remaining_time":29.79186416},
{"learn":[0.5660973306],"iteration":40,"passed_time":1.272992786,"remaining_time":29.77561174},
{"learn":[0.5633610588],"iteration":41,"passed_time":1.303375188,"remaining_time":29.72936738},
{"learn":[0.5611811945],"iteration":42,"passed_time":1.33038155,"remaining_time":29.60872426},
{"learn":[0.558452381],"iteration":43,"passed_time":1.355360089,"remaining_time":29.4482783},
{"learn":[0.5555031652],"iteration":44,"passed_time":1.383380451,"remaining_time":29.35840734},
{"learn":[0.5529937781],"iteration":45,"passed_time":1.410321351,"remaining_time":29.24883845},
{"learn":[0.5501216924],"iteration":46,"passed_time":1.440598895,"remaining_time":29.21044142},
{"learn":[0.5478457802],"iteration":47,"passed_time":1.472684228,"remaining_time":29.20823719},
{"learn":[0.5452481556],"iteration":48,"passed_time":1.501245526,"remaining_time":29.13641826},
{"learn":[0.5423177116],"iteration":49,"passed_time":1.528616003,"remaining_time":29.04370406},
{"learn":[0.5401491544],"iteration":50,"passed_time":1.559521467,"remaining_time":29.01933083},
{"learn":[0.537475754],"iteration":51,"passed_time":1.618021179,"remaining_time":29.49777072},
{"learn":[0.5355171293],"iteration":52,"passed_time":1.653697482,"remaining_time":29.54814179},
{"learn":[0.5332676129],"iteration":53,"passed_time":1.693764596,"remaining_time":29.67224645},
{"learn":[0.5315879706],"iteration":54,"passed_time":1.738880618,"remaining_time":29.87713061},
{"learn":[0.5290132858],"iteration":55,"passed_time":1.782127992,"remaining_time":30.04158615},
{"learn":[0.52675791],"iteration":56,"passed_time":1.815993566,"remaining_time":30.04354268},
{"learn":[0.5244348051],"iteration":57,"passed_time":1.845631938,"remaining_time":29.97560837},
{"learn":[0.5217627583],"iteration":58,"passed_time":1.878772286,"remaining_time":29.96482577},
{"learn":[0.5196319607],"iteration":59,"passed_time":1.918003873,"remaining_time":30.04872734},
{"learn":[0.5175174859],"iteration":60,"passed_time":1.949309056,"remaining_time":30.00657711},
{"learn":[0.5154886226],"iteration":61,"passed_time":1.987780176,"remaining_time":30.07319041},
{"learn":[0.5130488151],"iteration":62,"passed_time":2.014108416,"remaining_time":29.95586644},
{"learn":[0.5111413054],"iteration":63,"passed_time":2.047086962,"remaining_time":29.93864682},
{"learn":[0.5092414205],"iteration":64,"passed_time":2.080985261,"remaining_time":29.93417259},
{"learn":[0.5070452407],"iteration":65,"passed_time":2.114052453,"remaining_time":29.91704532},
{"learn":[0.5050591323],"iteration":66,"passed_time":2.14625258,"remaining_time":29.88736802},
{"learn":[0.5025522821],"iteration":67,"passed_time":2.193310202,"remaining_time":30.06125159},
{"learn":[0.5003491813],"iteration":68,"passed_time":2.22733703,"remaining_time":30.05290978},
{"learn":[0.4982946671],"iteration":69,"passed_time":2.261951424,"remaining_time":30.05164035},
{"learn":[0.4962596807],"iteration":70,"passed_time":2.295632862,"remaining_time":30.03722435},
{"learn":[0.4942857481],"iteration":71,"passed_time":2.334094874,"remaining_time":30.08388949},
{"learn":[0.4918050135],"iteration":72,"passed_time":2.365444337,"remaining_time":30.03790274},
{"learn":[0.4895775409],"iteration":73,"passed_time":2.397051873,"remaining_time":29.995541},
{"learn":[0.4878736272],"iteration":74,"passed_time":2.420620904,"remaining_time":29.85432448},
{"learn":[0.4859026977],"iteration":75,"passed_time":2.446368728,"remaining_time":29.74269348},
{"learn":[0.4844501081],"iteration":76,"passed_time":2.489563516,"remaining_time":29.8424302},
{"learn":[0.4830175364],"iteration":77,"passed_time":2.513488945,"remaining_time":29.71072829},
{"learn":[0.4811310714],"iteration":78,"passed_time":2.545019224,"remaining_time":29.67041399},
{"learn":[0.4791420864],"iteration":79,"passed_time":2.572205447,"remaining_time":29.58036263},
{"learn":[0.4768448191],"iteration":80,"passed_time":2.598164464,"remaining_time":29.47794003},
{"learn":[0.4748250998],"iteration":81,"passed_time":2.62888985,"remaining_time":29.43074247},
{"learn":[0.4728985615],"iteration":82,"passed_time":2.659100957,"remaining_time":29.37825997},
{"learn":[0.4703212914],"iteration":83,"passed_time":2.696941832,"remaining_time":29.40950855},
{"learn":[0.4687017464],"iteration":84,"passed_time":2.740299941,"remaining_time":29.49852289},
{"learn":[0.4666481934],"iteration":85,"passed_time":2.780931841,"remaining_time":29.55548492},
{"learn":[0.4650152758],"iteration":86,"passed_time":2.824159446,"remaining_time":29.63744338},
{"learn":[0.4628496431],"iteration":87,"passed_time":2.861613652,"remaining_time":29.6567233},
{"learn":[0.4606728433],"iteration":88,"passed_time":2.892442441,"remaining_time":29.60691083},
{"learn":[0.4588672782],"iteration":89,"passed_time":2.918652924,"remaining_time":29.51082401},
{"learn":[0.4571490247],"iteration":90,"passed_time":2.946781244,"remaining_time":29.43543023},
{"learn":[0.4554107833],"iteration":91,"passed_time":2.973256721,"remaining_time":29.34475111},
{"learn":[0.4532987493],"iteration":92,"passed_time":2.99952129,"remaining_time":29.25339581},
{"learn":[0.4512090849],"iteration":93,"passed_time":3.029343987,"remaining_time":29.19771971},
{"learn":[0.4493307951],"iteration":94,"passed_time":3.061507447,"remaining_time":29.16488673},
{"learn":[0.4475571025],"iteration":95,"passed_time":3.106086836,"remaining_time":29.24898437},
{"learn":[0.4454638461],"iteration":96,"passed_time":3.129975736,"remaining_time":29.13781536},
{"learn":[0.4436268889],"iteration":97,"passed_time":3.160519358,"remaining_time":29.08967817},
{"learn":[0.4416594186],"iteration":98,"passed_time":3.193931933,"remaining_time":29.06800678},
{"learn":[0.4401224534],"iteration":99,"passed_time":3.22755333,"remaining_time":29.04797997},
{"learn":[0.4385982421],"iteration":100,"passed_time":3.264866748,"remaining_time":29.06054659},
{"learn":[0.4367002318],"iteration":101,"passed_time":3.305158345,"remaining_time":29.09835484},
{"learn":[0.4345198643],"iteration":102,"passed_time":3.352272184,"remaining_time":29.1940597},
{"learn":[0.4331642748],"iteration":103,"passed_time":3.393918125,"remaining_time":29.23991},
{"learn":[0.4316757069],"iteration":104,"passed_time":3.426548412,"remaining_time":29.20724598},
{"learn":[0.4301836851],"iteration":105,"passed_time":3.474666127,"remaining_time":29.30520299},
{"learn":[0.428564171],"iteration":106,"passed_time":3.503079958,"remaining_time":29.23598507},
{"learn":[0.427015364],"iteration":107,"passed_time":3.528430985,"remaining_time":29.14222628},
{"learn":[0.4258064474],"iteration":108,"passed_time":3.559967755,"remaining_time":29.10028687},
{"learn":[0.4236267937],"iteration":109,"passed_time":3.587172828,"remaining_time":29.02348924},
{"learn":[0.4219159033],"iteration":110,"passed_time":3.622325037,"remaining_time":29.01123385},
{"learn":[0.4202672118],"iteration":111,"passed_time":3.660570303,"remaining_time":29.02309312},
{"learn":[0.4187315452],"iteration":112,"passed_time":3.690436768,"remaining_time":28.96829569},
{"learn":[0.4174570709],"iteration":113,"passed_time":3.719235858,"remaining_time":28.90564009},
{"learn":[0.4157162186],"iteration":114,"passed_time":3.749004472,"remaining_time":28.85103442},
{"learn":[0.4142257884],"iteration":115,"passed_time":3.789895151,"remaining_time":28.88161477},
{"learn":[0.412720122],"iteration":116,"passed_time":3.827547779,"remaining_time":28.8865358},
{"learn":[0.4110763425],"iteration":117,"passed_time":3.864989741,"remaining_time":28.88916061},
{"learn":[0.4096657381],"iteration":118,"passed_time":3.898015624,"remaining_time":28.85841819},
{"learn":[0.4081197616],"iteration":119,"passed_time":3.930010866,"remaining_time":28.82007968},
{"learn":[0.4067173782],"iteration":120,"passed_time":4.016571734,"remaining_time":29.17823599},
{"learn":[0.4055102612],"iteration":121,"passed_time":4.050511799,"remaining_time":29.15040459},
{"learn":[0.4043147527],"iteration":122,"passed_time":4.074885223,"remaining_time":29.05426293},
{"learn":[0.4031551565],"iteration":123,"passed_time":4.101548806,"remaining_time":28.97545769},
{"learn":[0.4020161221],"iteration":124,"passed_time":4.134718023,"remaining_time":28.94302616},
{"learn":[0.4005396435],"iteration":125,"passed_time":4.169776243,"remaining_time":28.92368601},
{"learn":[0.3993058827],"iteration":126,"passed_time":4.200786811,"remaining_time":28.8762747},
{"learn":[0.3977411055],"iteration":127,"passed_time":4.234902465,"remaining_time":28.85027305},
{"learn":[0.3963758377],"iteration":128,"passed_time":4.264377696,"remaining_time":28.79281374},
{"learn":[0.3947045568],"iteration":129,"passed_time":4.289302561,"remaining_time":28.70533253},
{"learn":[0.3932570353],"iteration":130,"passed_time":4.312935063,"remaining_time":28.61023336},
{"learn":[0.3919215833],"iteration":131,"passed_time":4.336303636,"remaining_time":28.51448149},
{"learn":[0.3904404759],"iteration":132,"passed_time":4.363457591,"remaining_time":28.44449422},
{"learn":[0.3887366681],"iteration":133,"passed_time":4.396133281,"remaining_time":28.41083151},
{"learn":[0.3871113451],"iteration":134,"passed_time":4.423225287,"remaining_time":28.34140647},
{"learn":[0.3852385244],"iteration":135,"passed_time":4.452584949,"remaining_time":28.28701027},
{"learn":[0.3840380417],"iteration":136,"passed_time":4.471407484,"remaining_time":28.16660335},
{"learn":[0.3827584919],"iteration":137,"passed_time":4.497792267,"remaining_time":28.09490532},
{"learn":[0.3815499993],"iteration":138,"passed_time":4.52524034,"remaining_time":28.03044556},
{"learn":[0.3805485355],"iteration":139,"passed_time":4.548463248,"remaining_time":27.94055995},
{"learn":[0.379339869],"iteration":140,"passed_time":4.57623064,"remaining_time":27.87930582},
{"learn":[0.3780901551],"iteration":141,"passed_time":4.599120835,"remaining_time":27.78905406},
{"learn":[0.3771530083],"iteration":142,"passed_time":4.628025459,"remaining_time":27.73578894},
{"learn":[0.3758878343],"iteration":143,"passed_time":4.655041881,"remaining_time":27.67163785},
{"learn":[0.3744883751],"iteration":144,"passed_time":4.680277856,"remaining_time":27.59750046},
{"learn":[0.3730773619],"iteration":145,"passed_time":4.703267205,"remaining_time":27.51089173},
{"learn":[0.3721647006],"iteration":146,"passed_time":4.729041486,"remaining_time":27.44130876},
{"learn":[0.3709395275],"iteration":147,"passed_time":4.757854964,"remaining_time":27.38981371},
{"learn":[0.3697295604],"iteration":148,"passed_time":4.784534856,"remaining_time":27.32643733},
{"learn":[0.3687487337],"iteration":149,"passed_time":4.811316267,"remaining_time":27.26412551},
{"learn":[0.367585653],"iteration":150,"passed_time":4.833523208,"remaining_time":27.17656426},
{"learn":[0.3666736695],"iteration":151,"passed_time":4.861853968,"remaining_time":27.1240274},
{"learn":[0.3652992048],"iteration":152,"passed_time":4.890524034,"remaining_time":27.07368534},
{"learn":[0.3642214524],"iteration":153,"passed_time":4.915566094,"remaining_time":27.00369426},
{"learn":[0.3629556797],"iteration":154,"passed_time":4.964289327,"remaining_time":27.06338375},
{"learn":[0.3618808175],"iteration":155,"passed_time":4.993546023,"remaining_time":27.01636438},
{"learn":[0.3610173107],"iteration":156,"passed_time":5.023748554,"remaining_time":26.97464988},
{"learn":[0.3601603864],"iteration":157,"passed_time":5.059933843,"remaining_time":26.9649639},
{"learn":[0.3590883721],"iteration":158,"passed_time":5.094514355,"remaining_time":26.94645643},
{"learn":[0.3580349057],"iteration":159,"passed_time":5.124451604,"remaining_time":26.90337092},
{"learn":[0.3566945316],"iteration":160,"passed_time":5.155220617,"remaining_time":26.86478322},
{"learn":[0.3556331404],"iteration":161,"passed_time":5.178641152,"remaining_time":26.78827954},
{"learn":[0.3542105326],"iteration":162,"passed_time":5.205650663,"remaining_time":26.73085647},
{"learn":[0.3533872695],"iteration":163,"passed_time":5.227771333,"remaining_time":26.64888314},
{"learn":[0.3523888701],"iteration":164,"passed_time":5.254159049,"remaining_time":26.58922913},
{"learn":[0.3514664297],"iteration":165,"passed_time":5.289234648,"remaining_time":26.57362468},
{"learn":[0.3499054852],"iteration":166,"passed_time":5.318971452,"remaining_time":26.531157},
{"learn":[0.3487495388],"iteration":167,"passed_time":5.350182642,"remaining_time":26.49614261},
{"learn":[0.3477554166],"iteration":168,"passed_time":5.376450305,"remaining_time":26.43686511},
{"learn":[0.3467692574],"iteration":169,"passed_time":5.405920689,"remaining_time":26.39361277},
{"learn":[0.3457557744],"iteration":170,"passed_time":5.426532248,"remaining_time":26.30757446},
{"learn":[0.3450420886],"iteration":171,"passed_time":5.45739323,"remaining_time":26.27163718},
{"learn":[0.3442226422],"iteration":172,"passed_time":5.48214529,"remaining_time":26.20655581},
{"learn":[0.3432357733],"iteration":173,"passed_time":5.51253425,"remaining_time":26.16869707},
{"learn":[0.3421279542],"iteration":174,"passed_time":5.545150889,"remaining_time":26.14142562},
{"learn":[0.3409365433],"iteration":175,"passed_time":5.578028021,"remaining_time":26.11531301},
{"learn":[0.3398067553],"iteration":176,"passed_time":5.604683041,"remaining_time":26.0601929},
{"learn":[0.3386858683],"iteration":177,"passed_time":5.634664263,"remaining_time":26.02075295},
{"learn":[0.3376789936],"iteration":178,"passed_time":5.663517953,"remaining_time":25.97624715},
{"learn":[0.3365143325],"iteration":179,"passed_time":5.686613185,"remaining_time":25.90568229},
{"learn":[0.3359373355],"iteration":180,"passed_time":5.710325683,"remaining_time":25.838435},
{"learn":[0.3351192252],"iteration":181,"passed_time":5.734745612,"remaining_time":25.77484566},
{"learn":[0.3342743377],"iteration":182,"passed_time":5.762347252,"remaining_time":25.7258891},
{"learn":[0.3332679604],"iteration":183,"passed_time":5.797422229,"remaining_time":25.71030728},
{"learn":[0.3325450423],"iteration":184,"passed_time":5.825122754,"remaining_time":25.66202727},
{"learn":[0.3317806854],"iteration":185,"passed_time":5.855522128,"remaining_time":25.62577963},
{"learn":[0.3307113763],"iteration":186,"passed_time":5.886278124,"remaining_time":25.591145},
{"learn":[0.3298345441],"iteration":187,"passed_time":5.914775541,"remaining_time":25.54679649},
{"learn":[0.3290475266],"iteration":188,"passed_time":5.949986777,"remaining_time":25.53142474},
{"learn":[0.3281982611],"iteration":189,"passed_time":5.99157085,"remaining_time":25.54301257},
{"learn":[0.3272586938],"iteration":190,"passed_time":6.032266934,"remaining_time":25.55028246},
{"learn":[0.3266135754],"iteration":191,"passed_time":6.065708208,"remaining_time":25.52652204},
{"learn":[0.3258567436],"iteration":192,"passed_time":6.104674432,"remaining_time":25.52576304},
{"learn":[0.3249041336],"iteration":193,"passed_time":6.145197076,"remaining_time":25.53107651},
{"learn":[0.3240771394],"iteration":194,"passed_time":6.186202514,"remaining_time":25.53791294},
{"learn":[0.323217187],"iteration":195,"passed_time":6.218449701,"remaining_time":25.50833449},
{"learn":[0.322467183],"iteration":196,"passed_time":6.267138165,"remaining_time":25.54574592},
{"learn":[0.3215733185],"iteration":197,"passed_time":6.316042081,"remaining_time":25.58316035},
{"learn":[0.3208047793],"iteration":198,"passed_time":6.339026336,"remaining_time":25.51537736},
{"learn":[0.3199895464],"iteration":199,"passed_time":6.378671815,"remaining_time":25.51468726},
{"learn":[0.3191794179],"iteration":200,"passed_time":6.412236126,"remaining_time":25.48943614},
{"learn":[0.3182067753],"iteration":201,"passed_time":6.459233497,"remaining_time":25.51716996},
{"learn":[0.3173712808],"iteration":202,"passed_time":6.496334135,"remaining_time":25.50531185},
{"learn":[0.3165011447],"iteration":203,"passed_time":6.534894041,"remaining_time":25.49890028},
{"learn":[0.3157584085],"iteration":204,"passed_time":6.582619776,"remaining_time":25.52772059},
{"learn":[0.3151213842],"iteration":205,"passed_time":6.620790072,"remaining_time":25.51896756},
{"learn":[0.3142447695],"iteration":206,"passed_time":6.652952188,"remaining_time":25.48691345},
{"learn":[0.3134702191],"iteration":207,"passed_time":6.685088821,"remaining_time":25.45476128},
{"learn":[0.3127674584],"iteration":208,"passed_time":6.719416231,"remaining_time":25.43090066},
{"learn":[0.3121343783],"iteration":209,"passed_time":6.751493719,"remaining_time":25.39847637},
{"learn":[0.3111944343],"iteration":210,"passed_time":6.779354559,"remaining_time":25.3502879},
{"learn":[0.3104518218],"iteration":211,"passed_time":6.809863771,"remaining_time":25.31213515},
{"learn":[0.3097324772],"iteration":212,"passed_time":6.864651693,"remaining_time":25.36376001},
{"learn":[0.3089439226],"iteration":213,"passed_time":6.903686333,"remaining_time":25.35653018},
{"learn":[0.3082021611],"iteration":214,"passed_time":6.98100704,"remaining_time":25.48879314},
{"learn":[0.3075876924],"iteration":215,"passed_time":7.021493922,"remaining_time":25.48542238},
{"learn":[0.3068979387],"iteration":216,"passed_time":7.046148496,"remaining_time":25.4245819},
{"learn":[0.3062719731],"iteration":217,"passed_time":7.078337591,"remaining_time":25.3911009},
{"learn":[0.3056393594],"iteration":218,"passed_time":7.104431533,"remaining_time":25.3358951},
{"learn":[0.3047874314],"iteration":219,"passed_time":7.132390926,"remaining_time":25.28756783},
{"learn":[0.3039526747],"iteration":220,"passed_time":7.160210318,"remaining_time":25.23893139},
{"learn":[0.3033066496],"iteration":221,"passed_time":7.184172651,"remaining_time":25.17696542},
{"learn":[0.3024420859],"iteration":222,"passed_time":7.21379156,"remaining_time":25.13504952},
{"learn":[0.3018366991],"iteration":223,"passed_time":7.243976327,"remaining_time":25.0952037},
{"learn":[0.3009371343],"iteration":224,"passed_time":7.272568721,"remaining_time":25.04995893},
{"learn":[0.3002019237],"iteration":225,"passed_time":7.298667523,"remaining_time":24.99632152},
{"learn":[0.2995081383],"iteration":226,"passed_time":7.327354431,"remaining_time":24.95173998},
{"learn":[0.2986373493],"iteration":227,"passed_time":7.355206444,"remaining_time":24.90447094},
{"learn":[0.2977638782],"iteration":228,"passed_time":7.379870793,"remaining_time":24.84663922},
{"learn":[0.2971219864],"iteration":229,"passed_time":7.409921756,"remaining_time":24.80712936},
{"learn":[0.2963851484],"iteration":230,"passed_time":7.438515056,"remaining_time":24.76284882},
{"learn":[0.2958048639],"iteration":231,"passed_time":7.462565012,"remaining_time":24.70366349},
{"learn":[0.2950446775],"iteration":232,"passed_time":7.49030896,"remaining_time":24.6569398},
{"learn":[0.2942708211],"iteration":233,"passed_time":7.518628252,"remaining_time":24.61226171},
{"learn":[0.2934233754],"iteration":234,"passed_time":7.545039398,"remaining_time":24.56151123},
{"learn":[0.2924456793],"iteration":235,"passed_time":7.572195858,"remaining_time":24.51337981},
{"learn":[0.2916300191],"iteration":236,"passed_time":7.60120293,"remaining_time":24.47138327},
{"learn":[0.2907366924],"iteration":237,"passed_time":7.626840924,"remaining_time":24.41870918},
{"learn":[0.2898618521],"iteration":238,"passed_time":7.657597092,"remaining_time":24.3825581},
{"learn":[0.2891347923],"iteration":239,"passed_time":7.695438983,"remaining_time":24.36889011},
{"learn":[0.2883656235],"iteration":240,"passed_time":7.72588878,"remaining_time":24.33174101},
{"learn":[0.2876997923],"iteration":241,"passed_time":7.756579911,"remaining_time":24.29540319},
{"learn":[0.2869457959],"iteration":242,"passed_time":7.786671305,"remaining_time":24.25724353},
{"learn":[0.2860551225],"iteration":243,"passed_time":7.820844011,"remaining_time":24.23179538},
{"learn":[0.2854694133],"iteration":244,"passed_time":7.854499543,"remaining_time":24.20468226},
{"learn":[0.2849905497],"iteration":245,"passed_time":7.881846209,"remaining_time":24.15817903},
{"learn":[0.2842700032],"iteration":246,"passed_time":7.908911571,"remaining_time":24.11097333},
{"learn":[0.2836856731],"iteration":247,"passed_time":7.948490844,"remaining_time":24.10187546},
{"learn":[0.28307232],"iteration":248,"passed_time":7.983807711,"remaining_time":24.07967707},
{"learn":[0.2823722465],"iteration":249,"passed_time":8.004933847,"remaining_time":24.01480154},
{"learn":[0.2817737576],"iteration":250,"passed_time":8.027483763,"remaining_time":23.95452326}
]}2393851],"iteration":251,"passed_time":8.313475975,"remaining_time":24.67650805},
{"learn":[0.3416259532],"iteration":252,"passed_time":8.345931374,"remaining_time":24.64193967},
{"learn":[0.3410366608],"iteration":253,"passed_time":8.381517405,"remaining_time":24.61658261},
{"learn":[0.3404402533],"iteration":254,"passed_time":8.40705766,"remaining_time":24.56179591},
{"learn":[0.3398533703],"iteration":255,"passed_time":8.430771977,"remaining_time":24.50193106},
{"learn":[0.339269062],"iteration":256,"passed_time":8.475444294,"remaining_time":24.50293817},
{"learn":[0.3384919845],"iteration":257,"passed_time":8.506076055,"remaining_time":24.46321098},
{"learn":[0.3375266381],"iteration":258,"passed_time":8.542896441,"remaining_time":24.4412597},
{"learn":[0.3370349599],"iteration":259,"passed_time":8.579507407,"remaining_time":24.418598},
{"learn":[0.3364666187],"iteration":260,"passed_time":8.623382756,"remaining_time":24.41639792},
{"learn":[0.3357082805],"iteration":261,"passed_time":8.661105284,"remaining_time":24.39654847},
{"learn":[0.3350268463],"iteration":262,"passed_time":8.693816876,"remaining_time":24.36252105},
{"learn":[0.3343437275],"iteration":263,"passed_time":8.725068186,"remaining_time":24.32443252},
{"learn":[0.3338572631],"iteration":264,"passed_time":8.757232851,"remaining_time":24.28892885},
{"learn":[0.3332031052],"iteration":265,"passed_time":8.793369273,"remaining_time":24.26440995},
{"learn":[0.332617088],"iteration":266,"passed_time":8.816736473,"remaining_time":24.20474844},
{"learn":[0.3321736999],"iteration":267,"passed_time":8.843503342,"remaining_time":24.15464346},
{"learn":[0.3314803404],"iteration":268,"passed_time":8.885821645,"remaining_time":24.14697257},
{"learn":[0.330978196],"iteration":269,"passed_time":8.91051704,"remaining_time":24.09139792},
{"learn":[0.3305029138],"iteration":270,"passed_time":8.937245788,"remaining_time":24.04152096},
{"learn":[0.3297793091],"iteration":271,"passed_time":8.967391013,"remaining_time":24.0009583},
{"learn":[0.3294051877],"iteration":272,"passed_time":8.99390558,"remaining_time":23.9508035},
{"learn":[0.3288902514],"iteration":273,"passed_time":9.027829593,"remaining_time":23.92045359},
{"learn":[0.3282602408],"iteration":274,"passed_time":9.065346617,"remaining_time":23.89955017},
{"learn":[0.3276548229],"iteration":275,"passed_time":9.094322844,"remaining_time":23.85612224},
{"learn":[0.3271737603],"iteration":276,"passed_time":9.128211467,"remaining_time":23.82562054},
{"learn":[0.326468184],"iteration":277,"passed_time":9.167916154,"remaining_time":23.81019951},
{"learn":[0.3257515813],"iteration":278,"passed_time":9.202802633,"remaining_time":23.78215304},
{"learn":[0.325083221],"iteration":279,"passed_time":9.227896927,"remaining_time":23.72887781},
{"learn":[0.3246642438],"iteration":280,"passed_time":9.256893764,"remaining_time":23.68578867},
{"learn":[0.324304632],"iteration":281,"passed_time":9.285233134,"remaining_time":23.6411255},
{"learn":[0.3236899985],"iteration":282,"passed_time":9.318956015,"remaining_time":23.61021718},
{"learn":[0.3229756843],"iteration":283,"passed_time":9.35717756,"remaining_time":23.59063075},
{"learn":[0.3222265626],"iteration":284,"passed_time":9.400818144,"remaining_time":23.58450868},
{"learn":[0.3214964249],"iteration":285,"passed_time":9.439238732,"remaining_time":23.5650925},
{"learn":[0.3207946572],"iteration":286,"passed_time":9.469310163,"remaining_time":23.5248019},
{"learn":[0.3201161127],"iteration":287,"passed_time":9.50219015,"remaining_time":23.49152565},
{"learn":[0.319324121],"iteration":288,"passed_time":9.536179376,"remaining_time":23.46098109},
{"learn":[0.3189754695],"iteration":289,"passed_time":9.570423905,"remaining_time":23.43103784},
{"learn":[0.3186605725],"iteration":290,"passed_time":9.604093446,"remaining_time":23.3996641},
{"learn":[0.3181227489],"iteration":291,"passed_time":9.640573926,"remaining_time":23.3750902},
{"learn":[0.3173373999],"iteration":292,"passed_time":9.687051898,"remaining_time":23.37455868},
{"learn":[0.3164972049],"iteration":293,"passed_time":9.722067913,"remaining_time":23.34619029},
{"learn":[0.3158839985],"iteration":294,"passed_time":9.769972172,"remaining_time":23.34857756},
{"learn":[0.3154735835],"iteration":295,"passed_time":9.814090516,"remaining_time":23.34162069},
{"learn":[0.3148652402],"iteration":296,"passed_time":9.845967538,"remaining_time":23.30543831},
{"learn":[0.3144050532],"iteration":297,"passed_time":9.878858036,"remaining_time":23.27167229},
{"learn":[0.313880347],"iteration":298,"passed_time":9.909095607,"remaining_time":23.23169238},
{"learn":[0.313380365],"iteration":299,"passed_time":9.946453425,"remaining_time":23.20839133},
{"learn":[0.3130664173],"iteration":300,"passed_time":9.97841908,"remaining_time":23.17247487},
{"learn":[0.3126997791],"iteration":301,"passed_time":10.01678454,"remaining_time":23.15137618},
{"learn":[0.3122259935],"iteration":302,"passed_time":10.05292958,"remaining_time":23.12505584},
{"learn":[0.311468663],"iteration":303,"passed_time":10.08815536,"remaining_time":23.09656623},
{"learn":[0.3103884789],"iteration":304,"passed_time":10.13176908,"remaining_time":23.08714594},
{"learn":[0.3097188943],"iteration":305,"passed_time":10.16786531,"remaining_time":23.06045269},
{"learn":[0.3093152847],"iteration":306,"passed_time":10.20247421,"remaining_time":23.0303408},
{"learn":[0.3086911414],"iteration":307,"passed_time":10.24343874,"remaining_time":23.01447926},
{"learn":[0.3083006135],"iteration":308,"passed_time":10.27902033,"remaining_time":22.98641764},
{"learn":[0.3079199895],"iteration":309,"passed_time":10.37832636,"remaining_time":23.10014576},
{"learn":[0.307617821],"iteration":310,"passed_time":10.42783271,"remaining_time":23.10217601},
{"learn":[0.3072813906],"iteration":311,"passed_time":10.46212203,"remaining_time":23.07032037},
{"learn":[0.3069504743],"iteration":312,"passed_time":10.48740039,"remaining_time":23.01867115},
{"learn":[0.306619491],"iteration":313,"passed_time":10.52873047,"remaining_time":23.00225828},
{"learn":[0.3062538117],"iteration":314,"passed_time":10.57032745,"remaining_time":22.98626762},
{"learn":[0.3055961123],"iteration":315,"passed_time":10.62683127,"remaining_time":23.0023816},
{"learn":[0.3049550552],"iteration":316,"passed_time":10.66135537,"remaining_time":22.9706805},
{"learn":[0.3046178113],"iteration":317,"passed_time":10.69236991,"remaining_time":22.93143484},
{"learn":[0.3041394958],"iteration":318,"passed_time":10.71917787,"remaining_time":22.8832606},
{"learn":[0.3036945162],"iteration":319,"passed_time":10.74600192,"remaining_time":22.83525408},
{"learn":[0.3032615063],"iteration":320,"passed_time":10.77192162,"remaining_time":22.7854666},
{"learn":[0.3023440612],"iteration":321,"passed_time":10.80743088,"remaining_time":22.75601907},
{"learn":[0.3018899486],"iteration":322,"passed_time":10.84147218,"remaining_time":22.72345716},
{"learn":[0.3014016891],"iteration":323,"passed_time":10.86882325,"remaining_time":22.67692751},
{"learn":[0.3009375534],"iteration":324,"passed_time":10.90176218,"remaining_time":22.64212145},
{"learn":[0.3002257452],"iteration":325,"passed_time":10.93998001,"remaining_time":22.61824087},
{"learn":[0.2998693468],"iteration":326,"passed_time":10.96719103,"remaining_time":22.57161945},
{"learn":[0.2992636392],"iteration":327,"passed_time":10.99497376,"remaining_time":22.5262877},
{"learn":[0.2988184255],"iteration":328,"passed_time":11.02412493,"remaining_time":22.48385358},
{"learn":[0.2984504769],"iteration":329,"passed_time":11.05671526,"remaining_time":22.4484825},
{"learn":[0.2981939351],"iteration":330,"passed_time":11.08922948,"remaining_time":22.41297439},
{"learn":[0.2976039491],"iteration":331,"passed_time":11.1173894,"remaining_time":22.36872325},
{"learn":[0.2969694886],"iteration":332,"passed_time":11.14660856,"remaining_time":22.32669042},
{"learn":[0.2965312004],"iteration":333,"passed_time":11.1704086,"remaining_time":22.27392853},
{"learn":[0.2960538638],"iteration":334,"passed_time":11.20451733,"remaining_time":22.24180305},
{"learn":[0.2955696722],"iteration":335,"passed_time":11.23275098,"remaining_time":22.19805551},
{"learn":[0.295197841],"iteration":336,"passed_time":11.26105976,"remaining_time":22.15454783},
{"learn":[0.2947307129],"iteration":337,"passed_time":11.29827192,"remaining_time":22.12856807},
{"learn":[0.2945277673],"iteration":338,"passed_time":11.32831922,"remaining_time":22.08855163},
{"learn":[0.2942262453],"iteration":339,"passed_time":11.36437189,"remaining_time":22.06025131},
{"learn":[0.2935361331],"iteration":340,"passed_time":11.40377966,"remaining_time":22.03838944},
{"learn":[0.2929548782],"iteration":341,"passed_time":11.4437808,"remaining_time":22.01756656},
{"learn":[0.2925012747],"iteration":342,"passed_time":11.48743218,"remaining_time":22.00362374},
{"learn":[0.2920854179],"iteration":343,"passed_time":11.51245352,"remaining_time":21.95398113},
{"learn":[0.2915101086],"iteration":344,"passed_time":11.53986727,"remaining_time":21.90902336},
{"learn":[0.2909978289],"iteration":345,"passed_time":11.56979315,"remaining_time":21.86891537},
{"learn":[0.2905842179],"iteration":346,"passed_time":11.59673106,"remaining_time":21.82324318},
{"learn":[0.2902533938],"iteration":347,"passed_time":11.62336699,"remaining_time":21.77711288},
{"learn":[0.2897348917],"iteration":348,"passed_time":11.66339088,"remaining_time":21.75606723},
{"learn":[0.2891436519],"iteration":349,"passed_time":11.69010543,"remaining_time":21.71019579},
{"learn":[0.2888094831],"iteration":350,"passed_time":11.717399,"remaining_time":21.66550413},
{"learn":[0.2885332377],"iteration":351,"passed_time":11.73946387,"remaining_time":21.61128575},
{"learn":[0.2879371452],"iteration":352,"passed_time":11.77738241,"remaining_time":21.58630713},
{"learn":[0.2874778962],"iteration":353,"passed_time":11.81290226,"remaining_time":21.55687814},
{"learn":[0.287049009],"iteration":354,"passed_time":11.85819893,"remaining_time":21.54517834},
{"learn":[0.2865178402],"iteration":355,"passed_time":11.89202992,"remaining_time":21.5125485},
{"learn":[0.2861381952],"iteration":356,"passed_time":11.92220102,"remaining_time":21.47332005},
{"learn":[0.2856501289],"iteration":357,"passed_time":11.95493921,"remaining_time":21.43874573},
{"learn":[0.2848628394],"iteration":358,"passed_time":11.98427568,"remaining_time":21.39810782},
{"learn":[0.2845152834],"iteration":359,"passed_time":12.00975923,"remaining_time":21.35068308},
{"learn":[0.2841892234],"iteration":360,"passed_time":12.04051686,"remaining_time":21.31271544},
{"learn":[0.2833281616],"iteration":361,"passed_time":12.06329025,"remaining_time":21.26071596},
{"learn":[0.2829025227],"iteration":362,"passed_time":12.09637585,"remaining_time":21.22697361},
{"learn":[0.2825801251],"iteration":363,"passed_time":12.12683213,"remaining_time":21.18864076},
{"learn":[0.2822831608],"iteration":364,"passed_time":12.15670764,"remaining_time":21.14934068},
{"learn":[0.2818305997],"iteration":365,"passed_time":12.19386609,"remaining_time":21.12270793},
{"learn":[0.2813522572],"iteration":366,"passed_time":12.22843907,"remaining_time":21.0915584},
{"learn":[0.2806085165],"iteration":367,"passed_time":12.25851573,"remaining_time":21.05266831},
{"learn":[0.2804284244],"iteration":368,"passed_time":12.29997756,"remaining_time":21.03329496},
{"learn":[0.2800012592],"iteration":369,"passed_time":12.34860375,"remaining_time":21.02600098},
{"learn":[0.2795650628],"iteration":370,"passed_time":12.38280025,"remaining_time":20.99401983},
{"learn":[0.2789875347],"iteration":371,"passed_time":12.41313817,"remaining_time":20.95551283},
{"learn":[0.2783365476],"iteration":372,"passed_time":12.45143139,"remaining_time":20.9304222},
{"learn":[0.2777472891],"iteration":373,"passed_time":12.4976143,"remaining_time":20.91846672},
{"learn":[0.2775032712],"iteration":374,"passed_time":12.54142065,"remaining_time":20.90236775},
{"learn":[0.2771628469],"iteration":375,"passed_time":12.59087524,"remaining_time":20.89549508},
{"learn":[0.2766928151],"iteration":376,"passed_time":12.6196656,"remaining_time":20.85424846},
{"learn":[0.2763363245],"iteration":377,"passed_time":12.65265046,"remaining_time":20.81996981},
{"learn":[0.2758432731],"iteration":378,"passed_time":12.68353576,"remaining_time":20.7822578},
{"learn":[0.2757126719],"iteration":379,"passed_time":12.69732403,"remaining_time":20.71668657},
{"learn":[0.2753579286],"iteration":380,"passed_time":12.72197341,"remaining_time":20.66903292},
{"learn":[0.2749585627],"iteration":381,"passed_time":12.75293184,"remaining_time":20.63170649},
{"learn":[0.2747380168],"iteration":382,"passed_time":12.78734424,"remaining_time":20.59997754},
{"learn":[0.2744451874],"iteration":383,"passed_time":12.81781845,"remaining_time":20.5619171},
{"learn":[0.2740784118],"iteration":384,"passed_time":12.85384888,"remaining_time":20.53277159},
{"learn":[0.2735897068],"iteration":385,"passed_time":12.88417953,"remaining_time":20.49452392},
{"learn":[0.2732615828],"iteration":386,"passed_time":12.92262369,"remaining_time":20.46916878},
{"learn":[0.272797246],"iteration":387,"passed_time":12.95849571,"remaining_time":20.43968911},
{"learn":[0.2722795062],"iteration":388,"passed_time":12.99478555,"remaining_time":20.41083283},
{"learn":[0.2717934351],"iteration":389,"passed_time":13.0261784,"remaining_time":20.37427903},
{"learn":[0.2714654486],"iteration":390,"passed_time":13.06439083,"remaining_time":20.34837345},
{"learn":[0.2710945632],"iteration":391,"passed_time":13.09530429,"remaining_time":20.31108421},
{"learn":[0.2704412406],"iteration":392,"passed_time":13.12546965,"remaining_time":20.27267195},
{"learn":[0.2701567316],"iteration":393,"passed_time":13.15083252,"remaining_time":20.22691499},
{"learn":[0.269877828],"iteration":394,"passed_time":13.18345468,"remaining_time":20.19237995},
{"learn":[0.2695944666],"iteration":395,"passed_time":13.20798651,"remaining_time":20.14551477},
{"learn":[0.2690184978],"iteration":396,"passed_time":13.23587118,"remaining_time":20.10385471},
{"learn":[0.2688181879],"iteration":397,"passed_time":13.31326387,"remaining_time":20.13714786},
{"learn":[0.2684251392],"iteration":398,"passed_time":13.35911431,"remaining_time":20.12237519},
{"learn":[0.2680418979],"iteration":399,"passed_time":13.39903773,"remaining_time":20.09855659},
{"learn":[0.2675216555],"iteration":400,"passed_time":13.42908259,"remaining_time":20.05990143},
{"learn":[0.2670329061],"iteration":401,"passed_time":13.45580069,"remaining_time":20.01634033},
{"learn":[0.26681604],"iteration":402,"passed_time":13.48750106,"remaining_time":19.9802435},
{"learn":[0.2663594049],"iteration":403,"passed_time":13.52691563,"remaining_time":19.9555488},
{"learn":[0.2658485801],"iteration":404,"passed_time":13.55980726,"remaining_time":19.92119832},
{"learn":[0.265432135],"iteration":405,"passed_time":13.59357537,"remaining_time":19.88813737},
{"learn":[0.2651279338],"iteration":406,"passed_time":13.6240146,"remaining_time":19.85022275},
{"learn":[0.2647008644],"iteration":407,"passed_time":13.64802288,"remaining_time":19.8030136},
{"learn":[0.2643879321],"iteration":408,"passed_time":13.68087082,"remaining_time":19.76869109},
{"learn":[0.2640211356],"iteration":409,"passed_time":13.71575533,"remaining_time":19.73730645},
{"learn":[0.2635590021],"iteration":410,"passed_time":13.75639665,"remaining_time":19.71415481},
{"learn":[0.2630654504],"iteration":411,"passed_time":13.78928565,"remaining_time":19.67985427},
{"learn":[0.2624896843],"iteration":412,"passed_time":13.82424159,"remaining_time":19.64849834},
{"learn":[0.2620258984],"iteration":413,"passed_time":13.8544539,"remaining_time":19.61041059},
{"learn":[0.261633317],"iteration":414,"passed_time":13.88895263,"remaining_time":19.57840311},
{"learn":[0.2613752454],"iteration":415,"passed_time":13.91906593,"remaining_time":19.54022717},
{"learn":[0.2610024449],"iteration":416,"passed_time":13.95191895,"remaining_time":19.50592026},
{"learn":[0.2607147763],"iteration":417,"passed_time":13.97666269,"remaining_time":19.46032939},
{"learn":[0.2601503978],"iteration":418,"passed_time":14.0091732,"remaining_time":19.4256077},
{"learn":[0.2595072776],"iteration":419,"passed_time":14.04162379,"remaining_time":19.3908138},
{"learn":[0.2589956696],"iteration":420,"passed_time":14.09126954,"remaining_time":19.37967949},
{"learn":[0.2585206632],"iteration":421,"passed_time":14.1222,"remaining_time":19.34272892},
{"learn":[0.2582530619],"iteration":422,"passed_time":14.14511824,"remaining_time":19.2948776},
{"learn":[0.2577980531],"iteration":423,"passed_time":14.17569967,"remaining_time":19.25755427},
{"learn":[0.2574153025],"iteration":424,"passed_time":14.20523841,"remaining_time":19.21885197},
{"learn":[0.2572853887],"iteration":425,"passed_time":14.24446217,"remaining_time":19.19324245},
{"learn":[0.2571025713],"iteration":426,"passed_time":14.27095241,"remaining_time":19.1504818},
{"learn":[0.2565801422],"iteration":427,"passed_time":14.30016675,"remaining_time":19.11143781},
{"learn":[0.2562972386],"iteration":428,"passed_time":14.33117465,"remaining_time":19.07482687}
]}_time":18.64073086},
{"learn":[0.2009633745],"iteration":429,"passed_time":14.03796754,"remaining_time":18.6084686},
{"learn":[0.2006362764],"iteration":430,"passed_time":14.06170655,"remaining_time":18.56406271},
{"learn":[0.2003667407],"iteration":431,"passed_time":14.07943925,"remaining_time":18.51185531},
{"learn":[0.2000060873],"iteration":432,"passed_time":14.11414399,"remaining_time":18.4820315},
{"learn":[0.1995500387],"iteration":433,"passed_time":14.14295837,"remaining_time":18.44450331},
{"learn":[0.19915362],"iteration":434,"passed_time":14.16856137,"remaining_time":18.40284407},
{"learn":[0.1987841765],"iteration":435,"passed_time":14.19595459,"remaining_time":18.36357428},
{"learn":[0.1983788544],"iteration":436,"passed_time":14.22424777,"remaining_time":18.3255183},
{"learn":[0.1981036672],"iteration":437,"passed_time":14.25191441,"remaining_time":18.28670296},
{"learn":[0.1978588322],"iteration":438,"passed_time":14.28284463,"remaining_time":18.25210897},
{"learn":[0.1976284824],"iteration":439,"passed_time":14.308133,"remaining_time":18.2103511},
{"learn":[0.1972224695],"iteration":440,"passed_time":14.34051653,"remaining_time":18.17766154},
{"learn":[0.1969391865],"iteration":441,"passed_time":14.37773487,"remaining_time":18.15107706},
{"learn":[0.1967513083],"iteration":442,"passed_time":14.40922163,"remaining_time":18.11723803},
{"learn":[0.1964800332],"iteration":443,"passed_time":14.44509875,"remaining_time":18.08890744},
{"learn":[0.1962159959],"iteration":444,"passed_time":14.47467939,"remaining_time":18.05269003},
{"learn":[0.1959241985],"iteration":445,"passed_time":14.50924792,"remaining_time":18.02269808},
{"learn":[0.1955671206],"iteration":446,"passed_time":14.55662637,"remaining_time":18.00853329},
{"learn":[0.1950838836],"iteration":447,"passed_time":14.58873092,"remaining_time":17.97540059},
{"learn":[0.1946390867],"iteration":448,"passed_time":14.62559867,"remaining_time":17.94811775},
{"learn":[0.1944857566],"iteration":449,"passed_time":14.66097741,"remaining_time":17.91897239},
{"learn":[0.1942542165],"iteration":450,"passed_time":14.68921562,"remaining_time":17.88110726},
{"learn":[0.1939121154],"iteration":451,"passed_time":14.71772342,"remaining_time":17.84361158},
{"learn":[0.1936793467],"iteration":452,"passed_time":14.74778192,"remaining_time":17.80802806},
{"learn":[0.1933863903],"iteration":453,"passed_time":14.77256767,"remaining_time":17.76612764},
{"learn":[0.1928913254],"iteration":454,"passed_time":14.80123987,"remaining_time":17.72895765},
{"learn":[0.1925531008],"iteration":455,"passed_time":14.8239516,"remaining_time":17.68471419},
{"learn":[0.1921109562],"iteration":456,"passed_time":14.85224243,"remaining_time":17.64719396},
{"learn":[0.1918191205],"iteration":457,"passed_time":14.87301354,"remaining_time":17.60081515},
{"learn":[0.1913178071],"iteration":458,"passed_time":14.88851959,"remaining_time":17.54834226},
{"learn":[0.1911047184],"iteration":459,"passed_time":14.90561525,"remaining_time":17.49789616}
]}.889092689},
{"learn":[0.2526582609],"iteration":460,"passed_time":7.591017364,"remaining_time":8.875397742},
{"learn":[0.2520117237],"iteration":461,"passed_time":7.622069744,"remaining_time":8.875916715},
{"learn":[0.2514842766],"iteration":462,"passed_time":7.657117888,"remaining_time":8.880933706},
{"learn":[0.2512049433],"iteration":463,"passed_time":7.675340133,"remaining_time":8.866341188},
{"learn":[0.2509891948],"iteration":464,"passed_time":7.686228045,"remaining_time":8.843294632},
{"learn":[0.2504925525],"iteration":465,"passed_time":7.697696656,"remaining_time":8.820965696},
{"learn":[0.2502023224],"iteration":466,"passed_time":7.718428228,"remaining_time":8.809255344},
{"learn":[0.249934831],"iteration":467,"passed_time":7.727956355,"remaining_time":8.784770899},
{"learn":[0.2496589643],"iteration":468,"passed_time":7.739342812,"remaining_time":8.762454228},
{"learn":[0.2492993522],"iteration":469,"passed_time":7.754534619,"remaining_time":8.744475209},
{"learn":[0.2489747997],"iteration":470,"passed_time":7.766021624,"remaining_time":8.722347005},
{"learn":[0.248505572],"iteration":471,"passed_time":7.782316,"remaining_time":8.705641627},
{"learn":[0.2481932178],"iteration":472,"passed_time":7.796325939,"remaining_time":8.686392748},
{"learn":[0.2479341255],"iteration":473,"passed_time":7.817664622,"remaining_time":8.675298716},
{"learn":[0.2477073717],"iteration":474,"passed_time":7.836558444,"remaining_time":8.661459333},
{"learn":[0.2475540232],"iteration":475,"passed_time":7.852819452,"remaining_time":8.644700405},
{"learn":[0.247148655],"iteration":476,"passed_time":7.864051433,"remaining_time":8.622429558},
{"learn":[0.246693041],"iteration":477,"passed_time":7.887246389,"remaining_time":8.61326907},
{"learn":[0.2463357557],"iteration":478,"passed_time":7.900279908,"remaining_time":8.592997561},
{"learn":[0.2460463298],"iteration":479,"passed_time":7.92160476,"remaining_time":8.58173849},
{"learn":[0.2457304364],"iteration":480,"passed_time":7.944121272,"remaining_time":8.571723368},
{"learn":[0.245423358],"iteration":481,"passed_time":7.958318472,"remaining_time":8.552715702},
{"learn":[0.2451607719],"iteration":482,"passed_time":7.973816667,"remaining_time":8.535120531},
{"learn":[0.2447658734],"iteration":483,"passed_time":7.995017845,"remaining_time":8.523614067},
{"learn":[0.2443807907],"iteration":484,"passed_time":8.015879714,"remaining_time":8.511707325},
{"learn":[0.2441005357],"iteration":485,"passed_time":8.029550046,"remaining_time":8.492157868},
{"learn":[0.2439030793],"iteration":486,"passed_time":8.051260632,"remaining_time":8.481102062},
{"learn":[0.2435670676],"iteration":487,"passed_time":8.067870747,"remaining_time":8.464651275},
{"learn":[0.2431987481],"iteration":488,"passed_time":8.081542269,"remaining_time":8.445129038},
{"learn":[0.242923182],"iteration":489,"passed_time":8.098211996,"remaining_time":8.428751261},
{"learn":[0.2424077443],"iteration":490,"passed_time":8.114359433,"remaining_time":8.411830858},
{"learn":[0.2420335248],"iteration":491,"passed_time":8.128744581,"remaining_time":8.393093998},
{"learn":[0.2418254389],"iteration":492,"passed_time":8.14379608,"remaining_time":8.375060066},
{"learn":[0.2416822781],"iteration":493,"passed_time":8.165541842,"remaining_time":8.363895086},
{"learn":[0.2413801547],"iteration":494,"passed_time":8.185394592,"remaining_time":8.350756099},
{"learn":[0.2412376676],"iteration":495,"passed_time":8.205114231,"remaining_time":8.337454783},
{"learn":[0.2407154005],"iteration":496,"passed_time":8.21458192,"remaining_time":8.313751923},
{"learn":[0.2402899153],"iteration":497,"passed_time":8.225518331,"remaining_time":8.291586751},
{"learn":[0.2401147455],"iteration":498,"passed_time":8.241975108,"remaining_time":8.275009076},
{"learn":[0.2398411835],"iteration":499,"passed_time":8.260720788,"remaining_time":8.260720788},
{"learn":[0.239607798],"iteration":500,"passed_time":8.275003266,"remaining_time":8.24196932},
{"learn":[0.2392157502],"iteration":501,"passed_time":8.290921132,"remaining_time":8.224858015},
{"learn":[0.2390824314],"iteration":502,"passed_time":8.306505009,"remaining_time":8.20742145},
{"learn":[0.2387789414],"iteration":503,"passed_time":8.321545557,"remaining_time":8.189457532},
{"learn":[0.2385597825],"iteration":504,"passed_time":8.331732618,"remaining_time":8.166747814},
{"learn":[0.2384843818],"iteration":505,"passed_time":8.34439743,"remaining_time":8.146506582},
{"learn":[0.2381919186],"iteration":506,"passed_time":8.36205806,"remaining_time":8.131153104},
{"learn":[0.2378888558],"iteration":507,"passed_time":8.37750746,"remaining_time":8.113648958},
{"learn":[0.2375439937],"iteration":508,"passed_time":8.393396157,"remaining_time":8.096576647},
{"learn":[0.2371733007],"iteration":509,"passed_time":8.411196685,"remaining_time":8.081345834},
{"learn":[0.2368979916],"iteration":510,"passed_time":8.4255084,"remaining_time":8.062766356},
{"learn":[0.2367057234],"iteration":511,"passed_time":8.43634079,"remaining_time":8.040887316},
{"learn":[0.2364933698],"iteration":512,"passed_time":8.454154472,"remaining_time":8.025678807},
{"learn":[0.2363795582],"iteration":513,"passed_time":8.470780111,"remaining_time":8.009336837},
{"learn":[0.2361462462],"iteration":514,"passed_time":8.485377804,"remaining_time":7.991083952},
{"learn":[0.2358540361],"iteration":515,"passed_time":8.518280849,"remaining_time":7.99001537},
{"learn":[0.2354322581],"iteration":516,"passed_time":8.540361922,"remaining_time":7.978713362},
{"learn":[0.2352292149],"iteration":517,"passed_time":8.558548192,"remaining_time":7.963745615},
{"learn":[0.2350769496],"iteration":518,"passed_time":8.571978048,"remaining_time":7.944357305},
{"learn":[0.2345963056],"iteration":519,"passed_time":8.590837042,"remaining_time":7.930003423},
{"learn":[0.2342591735],"iteration":520,"passed_time":8.608186916,"remaining_time":7.914244784},
{"learn":[0.2340437619],"iteration":521,"passed_time":8.625023558,"remaining_time":7.898010078},
{"learn":[0.2338086531],"iteration":522,"passed_time":8.641967366,"remaining_time":7.88187081},
{"learn":[0.2335986551],"iteration":523,"passed_time":8.658114462,"remaining_time":7.86500474},
{"learn":[0.2334290389],"iteration":524,"passed_time":8.679374291,"remaining_time":7.852767215},
{"learn":[0.2332607071],"iteration":525,"passed_time":8.703475836,"remaining_time":7.843056172},
{"learn":[0.2329303376],"iteration":526,"passed_time":8.723192785,"remaining_time":7.829355194},
{"learn":[0.2327027723],"iteration":527,"passed_time":8.74076015,"remaining_time":7.813709831},
{"learn":[0.2323795004],"iteration":528,"passed_time":8.758015448,"remaining_time":7.797779349},
{"learn":[0.2320221364],"iteration":529,"passed_time":8.776213846,"remaining_time":7.782680203},
{"learn":[0.2317871775],"iteration":530,"passed_time":8.794181675,"remaining_time":7.767365736},
{"learn":[0.2314657508],"iteration":531,"passed_time":8.808970371,"remaining_time":7.749244612},
{"learn":[0.2313568493],"iteration":532,"passed_time":8.832496247,"remaining_time":7.738791271},
{"learn":[0.2309740631],"iteration":533,"passed_time":8.844094136,"remaining_time":7.717879901},
{"learn":[0.2306122072],"iteration":534,"passed_time":8.857447635,"remaining_time":7.698529253},
{"learn":[0.2302575206],"iteration":535,"passed_time":8.87153508,"remaining_time":7.679836337},
{"learn":[0.2300228399],"iteration":536,"passed_time":8.887944859,"remaining_time":7.663162886},
{"learn":[0.2298127521],"iteration":537,"passed_time":8.90162939,"remaining_time":7.644150145},
{"learn":[0.2296193441],"iteration":538,"passed_time":8.918586801,"remaining_time":7.627956429},
{"learn":[0.2293778658],"iteration":539,"passed_time":8.932141369,"remaining_time":7.608861166},
{"learn":[0.2291752921],"iteration":540,"passed_time":8.94045191,"remaining_time":7.585337203},
{"learn":[0.2288953295],"iteration":541,"passed_time":8.960027687,"remaining_time":7.571388709},
{"learn":[0.2285621235],"iteration":542,"passed_time":8.979598975,"remaining_time":7.557415712},
{"learn":[0.2283186852],"iteration":543,"passed_time":8.989204893,"remaining_time":7.535068808},
{"learn":[0.2280100886],"iteration":544,"passed_time":9.011239543,"remaining_time":7.52314494},
{"learn":[0.2278097613],"iteration":545,"passed_time":9.033219619,"remaining_time":7.511138657},
{"learn":[0.2275786961],"iteration":546,"passed_time":9.053009567,"remaining_time":7.497282146},
{"learn":[0.2273721194],"iteration":547,"passed_time":9.066220476,"remaining_time":7.477977473},
{"learn":[0.2270961205],"iteration":548,"passed_time":9.086932629,"remaining_time":7.464857223},
{"learn":[0.2268824767],"iteration":549,"passed_time":9.1031138,"remaining_time":7.4480022},
{"learn":[0.2266011428],"iteration":550,"passed_time":9.121670124,"remaining_time":7.433085092},
{"learn":[0.2263046792],"iteration":551,"passed_time":9.133239062,"remaining_time":7.412483876},
{"learn":[0.2259374235],"iteration":552,"passed_time":9.156012145,"remaining_time":7.400971842},
{"learn":[0.2258067226],"iteration":553,"passed_time":9.166395891,"remaining_time":7.379445068},
{"learn":[0.2255155816],"iteration":554,"passed_time":9.196824146,"remaining_time":7.374030171},
{"learn":[0.2254036639],"iteration":555,"passed_time":9.210022746,"remaining_time":7.354766366},
{"learn":[0.2250790743],"iteration":556,"passed_time":9.228419004,"remaining_time":7.339658202},
{"learn":[0.2248412163],"iteration":557,"passed_time":9.246507232,"remaining_time":7.324294259},
{"learn":[0.224657742],"iteration":558,"passed_time":9.26338096,"remaining_time":7.307962439},
{"learn":[0.2245092427],"iteration":559,"passed_time":9.27618798,"remaining_time":7.288433413},
{"learn":[0.2243395465],"iteration":560,"passed_time":9.293040016,"remaining_time":7.272093702},
{"learn":[0.2241802673],"iteration":561,"passed_time":9.306699939,"remaining_time":7.253264365},
{"learn":[0.2240724088],"iteration":562,"passed_time":9.316543527,"remaining_time":7.231491157},
{"learn":[0.2238640206],"iteration":563,"passed_time":9.338229396,"remaining_time":7.218914923},
{"learn":[0.223577616],"iteration":564,"passed_time":9.349716374,"remaining_time":7.1984542},
{"learn":[0.2235154069],"iteration":565,"passed_time":9.369783758,"remaining_time":7.184604507},
{"learn":[0.2232384405],"iteration":566,"passed_time":9.390472158,"remaining_time":7.171207133},
{"learn":[0.2230274392],"iteration":567,"passed_time":9.406674542,"remaining_time":7.154372187},
{"learn":[0.2228649181],"iteration":568,"passed_time":9.423070893,"remaining_time":7.137686388},
{"learn":[0.2226503465],"iteration":569,"passed_time":9.44201819,"remaining_time":7.122926003},
{"learn":[0.2224197586],"iteration":570,"passed_time":9.457877057,"remaining_time":7.105830574},
{"learn":[0.2222177127],"iteration":571,"passed_time":9.473974747,"remaining_time":7.088918167},
{"learn":[0.2220560165],"iteration":572,"passed_time":9.487391914,"remaining_time":7.070011077},
{"learn":[0.2218930039],"iteration":573,"passed_time":9.504998959,"remaining_time":7.054232677},
{"learn":[0.2217038922],"iteration":574,"passed_time":9.514846807,"remaining_time":7.032712857},
{"learn":[0.2214828203],"iteration":575,"passed_time":9.528026739,"remaining_time":7.013686349},
{"learn":[0.2212353651],"iteration":576,"passed_time":9.541140978,"remaining_time":6.994631948},
{"learn":[0.220966365],"iteration":577,"passed_time":9.552671404,"remaining_time":6.974441752},
{"learn":[0.2207660865],"iteration":578,"passed_time":9.569040986,"remaining_time":6.957800095},
{"learn":[0.2205598475],"iteration":579,"passed_time":9.578168592,"remaining_time":6.935915188},
{"learn":[0.2203614599],"iteration":580,"passed_time":9.60242849,"remaining_time":6.924987156},
{"learn":[0.2199463205],"iteration":581,"passed_time":9.621929384,"remaining_time":6.910595331},
{"learn":[0.2198665228],"iteration":582,"passed_time":9.639699073,"remaining_time":6.894947708},
{"learn":[0.2197108243],"iteration":583,"passed_time":9.657432419,"remaining_time":6.879266928},
{"learn":[0.2194201964],"iteration":584,"passed_time":9.674165468,"remaining_time":6.86286952},
{"learn":[0.2190756755],"iteration":585,"passed_time":9.695378963,"remaining_time":6.849636332},
{"learn":[0.2189280261],"iteration":586,"passed_time":9.718541126,"remaining_time":6.837746993},
{"learn":[0.2186465747],"iteration":587,"passed_time":9.738245093,"remaining_time":6.823396222},
{"learn":[0.2184788032],"iteration":588,"passed_time":9.759966284,"remaining_time":6.810434877},
{"learn":[0.2183501928],"iteration":589,"passed_time":9.782212393,"remaining_time":6.797808612},
{"learn":[0.2179859237],"iteration":590,"passed_time":9.799712064,"remaining_time":6.781865032},
{"learn":[0.217737584],"iteration":591,"passed_time":9.814520072,"remaining_time":6.764061131},
{"learn":[0.2176429197],"iteration":592,"passed_time":9.826420387,"remaining_time":6.744271665},
{"learn":[0.2174092281],"iteration":593,"passed_time":9.839798789,"remaining_time":6.725519038},
{"learn":[0.2172426642],"iteration":594,"passed_time":9.855270206,"remaining_time":6.708209132},
{"learn":[0.2171448331],"iteration":595,"passed_time":9.875294139,"remaining_time":6.693991329},
{"learn":[0.217059259],"iteration":596,"passed_time":9.890322657,"remaining_time":6.676381961},
{"learn":[0.216732159],"iteration":597,"passed_time":9.909219169,"remaining_time":6.661381448},
{"learn":[0.2166031521],"iteration":598,"passed_time":9.92528316,"remaining_time":6.644471698},
{"learn":[0.2164856213],"iteration":599,"passed_time":9.941691458,"remaining_time":6.627794306},
{"learn":[0.2160336133],"iteration":600,"passed_time":9.958100223,"remaining_time":6.611118118},
{"learn":[0.2158709168],"iteration":601,"passed_time":9.976002595,"remaining_time":6.595430287},
{"learn":[0.2157762241],"iteration":602,"passed_time":9.993784868,"remaining_time":6.579656041},
{"learn":[0.2156578605],"iteration":603,"passed_time":10.01457223,"remaining_time":6.565845372},
{"learn":[0.2152396233],"iteration":604,"passed_time":10.02914897,"remaining_time":6.547956769},
{"learn":[0.2149953834],"iteration":605,"passed_time":10.03944079,"remaining_time":6.527293184},
{"learn":[0.2149372351],"iteration":606,"passed_time":10.05254996,"remaining_time":6.508487864},
{"learn":[0.2147915709],"iteration":607,"passed_time":10.06809318,"remaining_time":6.491270605},
{"learn":[0.2146988969],"iteration":608,"passed_time":10.08667516,"remaining_time":6.476009834},
{"learn":[0.2143855345],"iteration":609,"passed_time":10.10221793,"remaining_time":6.458795071},
{"learn":[0.2141853942],"iteration":610,"passed_time":10.12112722,"remaining_time":6.443729114},
{"learn":[0.2140104097],"iteration":611,"passed_time":10.1368399,"remaining_time":6.426623987},
{"learn":[0.213780125],"iteration":612,"passed_time":10.15327535,"remaining_time":6.409979708},
{"learn":[0.213610986],"iteration":613,"passed_time":10.17785847,"remaining_time":6.398458256},
{"learn":[0.2134755202],"iteration":614,"passed_time":10.19712308,"remaining_time":6.383564855},
{"learn":[0.2132267736],"iteration":615,"passed_time":10.21691166,"remaining_time":6.36898389},
{"learn":[0.2130255146],"iteration":616,"passed_time":10.24452545,"remaining_time":6.359243513},
{"learn":[0.212706755],"iteration":617,"passed_time":10.26738164,"remaining_time":6.346504509},
{"learn":[0.212579468],"iteration":618,"passed_time":10.28535668,"remaining_time":6.330728427},
{"learn":[0.2124543415],"iteration":619,"passed_time":10.29850481,"remaining_time":6.311986821},
{"learn":[0.2121732943],"iteration":620,"passed_time":10.32060881,"remaining_time":6.298729049},
{"learn":[0.2119953451],"iteration":621,"passed_time":10.34310008,"remaining_time":6.285678181},
{"learn":[0.2118813024],"iteration":622,"passed_time":10.36843369,"remaining_time":6.274317016},
{"learn":[0.2117525149],"iteration":623,"passed_time":10.39281286,"remaining_time":6.262335952},
{"learn":[0.2114783266],"iteration":624,"passed_time":10.41093564,"remaining_time":6.246561381},
{"learn":[0.2112471202],"iteration":625,"passed_time":10.432638,"remaining_time":6.232917911},
{"learn":[0.2111036648],"iteration":626,"passed_time":10.451096,"remaining_time":6.217318674},
{"learn":[0.2109189517],"iteration":627,"passed_time":10.46214995,"remaining_time":6.197324494},
{"learn":[0.2106632167],"iteration":628,"passed_time":10.48021576,"remaining_time":6.18149451},
{"learn":[0.2104396682],"iteration":629,"passed_time":10.50289943,"remaining_time":6.168369508},
{"learn":[0.2102419864],"iteration":630,"passed_time":10.5190639,"remaining_time":6.151401867},
{"learn":[0.209970025],"iteration":631,"passed_time":10.53620944,"remaining_time":6.135008029},
{"learn":[0.2098365763],"iteration":632,"passed_time":10.55290646,"remaining_time":6.118351769},
{"learn":[0.2096860469],"iteration":633,"passed_time":10.57601207,"remaining_time":6.105394983},
{"learn":[0.2095466204],"iteration":634,"passed_time":10.59376029,"remaining_time":6.089326778},
{"learn":[0.2091728008],"iteration":635,"passed_time":10.61056899,"remaining_time":6.072715587},
{"learn":[0.2090469659],"iteration":636,"passed_time":10.62553099,"remaining_time":6.055051411},
{"learn":[0.2089261525],"iteration":637,"passed_time":10.64478292,"remaining_time":6.039829808},
{"learn":[0.2087768869],"iteration":638,"passed_time":10.66356221,"remaining_time":6.024328573},
{"learn":[0.2086814391],"iteration":639,"passed_time":10.6905869,"remaining_time":6.013455134},
{"learn":[0.2084416695],"iteration":640,"passed_time":10.7099393,"remaining_time":5.998234333},
{"learn":[0.2083152515],"iteration":641,"passed_time":10.73456545,"remaining_time":5.985941479},
{"learn":[0.2080538385],"iteration":642,"passed_time":10.75573667,"remaining_time":5.971692057},
{"learn":[0.2079840363],"iteration":643,"passed_time":10.77444768,"remaining_time":5.956061137},
{"learn":[0.2077887957],"iteration":644,"passed_time":10.79340467,"remaining_time":5.94055606},
{"learn":[0.2075119105],"iteration":645,"passed_time":10.81482047,"remaining_time":5.926387686},
{"learn":[0.2072907315],"iteration":646,"passed_time":10.83816122,"remaining_time":5.913247158},
{"learn":[0.2070782003],"iteration":647,"passed_time":10.84931635,"remaining_time":5.893455793},
{"learn":[0.2069040062],"iteration":648,"passed_time":10.86398576,"remaining_time":5.875591681},
{"learn":[0.2066187755],"iteration":649,"passed_time":10.92413781,"remaining_time":5.882228053},
{"learn":[0.206409152],"iteration":650,"passed_time":10.94606334,"remaining_time":5.86816606},
{"learn":[0.2062070076],"iteration":651,"passed_time":10.97897942,"remaining_time":5.859946073},
{"learn":[0.2059863797],"iteration":652,"passed_time":10.99027829,"remaining_time":5.840163194},
{"learn":[0.2059410698],"iteration":653,"passed_time":11.00380729,"remaining_time":5.82158612},
{"learn":[0.2057868044],"iteration":654,"passed_time":11.01494725,"remaining_time":5.801766111},
{"learn":[0.2056634469],"iteration":655,"passed_time":11.02949746,"remaining_time":5.783760863},
{"learn":[0.2054993579],"iteration":656,"passed_time":11.05752663,"remaining_time":5.772803094},
{"learn":[0.2052436212],"iteration":657,"passed_time":11.0941682,"remaining_time":5.766269792},
{"learn":[0.2051650864],"iteration":658,"passed_time":11.12300153,"remaining_time":5.755604737},
{"learn":[0.2047383941],"iteration":659,"passed_time":11.13546254,"remaining_time":5.736450399},
{"learn":[0.2044135531],"iteration":660,"passed_time":11.15342702,"remaining_time":5.720138819},
{"learn":[0.2042423348],"iteration":661,"passed_time":11.17320439,"remaining_time":5.704747862},
{"learn":[0.2040296741],"iteration":662,"passed_time":11.18818528,"remaining_time":5.686905639},
{"learn":[0.2037906353],"iteration":663,"passed_time":11.20753846,"remaining_time":5.67128452},
{"learn":[0.2035033349],"iteration":664,"passed_time":11.22115398,"remaining_time":5.652761779},
{"learn":[0.2033361698],"iteration":665,"passed_time":11.23862238,"remaining_time":5.636185998},
{"learn":[0.2031458098],"iteration":666,"passed_time":11.25372453,"remaining_time":5.618426189},
{"learn":[0.2029200758],"iteration":667,"passed_time":11.26711006,"remaining_time":5.59982117},
{"learn":[0.2026588563],"iteration":668,"passed_time":11.28370837,"remaining_time":5.582821332},
{"learn":[0.2024811092],"iteration":669,"passed_time":11.29931784,"remaining_time":5.565335652},
{"learn":[0.2023352998],"iteration":670,"passed_time":11.31556152,"remaining_time":5.548166526},
{"learn":[0.2021687877],"iteration":671,"passed_time":11.33099231,"remaining_time":5.530603388},
{"learn":[0.2019592126],"iteration":672,"passed_time":11.34355221,"remaining_time":5.511651667},
{"learn":[0.2016526875],"iteration":673,"passed_time":11.35883147,"remaining_time":5.494034212},
{"learn":[0.2014486937],"iteration":674,"passed_time":11.37408343,"remaining_time":5.476410542},
{"learn":[0.2012831266],"iteration":675,"passed_time":11.38740755,"remaining_time":5.457869893},
{"learn":[0.2010185606],"iteration":676,"passed_time":11.40396884,"remaining_time":5.44088912},
{"learn":[0.2008384829],"iteration":677,"passed_time":11.42113994,"remaining_time":5.424199204},
{"learn":[0.2005029917],"iteration":678,"passed_time":11.44075666,"remaining_time":5.408664048},
{"learn":[0.2003642493],"iteration":679,"passed_time":11.45883189,"remaining_time":5.392391476},
{"learn":[0.2000459856],"iteration":680,"passed_time":11.47473931,"remaining_time":5.375098151},
{"learn":[0.1998665376],"iteration":681,"passed_time":11.48484942,"remaining_time":5.355105742},
{"learn":[0.199737522],"iteration":682,"passed_time":11.49965667,"remaining_time":5.337322347},
{"learn":[0.1994000354],"iteration":683,"passed_time":11.51356645,"remaining_time":5.31913304},
{"learn":[0.1993082615],"iteration":684,"passed_time":11.5290395,"remaining_time":5.3016751},
{"learn":[0.1991706119],"iteration":685,"passed_time":11.5426699,"remaining_time":5.283379517},
{"learn":[0.1988761494],"iteration":686,"passed_time":11.55560078,"remaining_time":5.264778815},
{"learn":[0.1986468339],"iteration":687,"passed_time":11.57032721,"remaining_time":5.247008852},
{"learn":[0.1985723324],"iteration":688,"passed_time":11.58220457,"remaining_time":5.227961715},
{"learn":[0.1983912579],"iteration":689,"passed_time":11.59961624,"remaining_time":5.211421787},
{"learn":[0.197943525],"iteration":690,"passed_time":11.61425553,"remaining_time":5.193639594},
{"learn":[0.1977783943],"iteration":691,"passed_time":11.63096396,"remaining_time":5.176787426},
{"learn":[0.1976275107],"iteration":692,"passed_time":11.64384493,"remaining_time":5.158240105},
{"learn":[0.1975268851],"iteration":693,"passed_time":11.65404123,"remaining_time":5.138525383},
{"learn":[0.1974112184],"iteration":694,"passed_time":11.67138219,"remaining_time":5.121973481},
{"learn":[0.1972227779],"iteration":695,"passed_time":11.68757138,"remaining_time":5.104916233},
{"learn":[0.1971052496],"iteration":696,"passed_time":11.70393943,"remaining_time":5.087939238},
{"learn":[0.1968409229],"iteration":697,"passed_time":11.71867591,"remaining_time":5.070258059},
{"learn":[0.196683983],"iteration":698,"passed_time":11.73614852,"remaining_time":5.053763524},
{"learn":[0.1966187047],"iteration":699,"passed_time":11.75462656,"remaining_time":5.037697099},
{"learn":[0.1963755031],"iteration":700,"passed_time":11.76736021,"remaining_time":5.019173611},
{"learn":[0.1962034659],"iteration":701,"passed_time":11.78163957,"remaining_time":5.001322782},
{"learn":[0.1960575209],"iteration":702,"passed_time":11.79310581,"remaining_time":4.982293637},
{"learn":[0.1959570689],"iteration":703,"passed_time":11.80448701,"remaining_time":4.963250222},
{"learn":[0.1957371727],"iteration":704,"passed_time":11.82052871,"remaining_time":4.946178678},
{"learn":[0.1956726865],"iteration":705,"passed_time":11.8321776,"remaining_time":4.927280757},
{"learn":[0.1955555798],"iteration":706,"passed_time":11.85096682,"remaining_time":4.911362488},
{"learn":[0.1953418566],"iteration":707,"passed_time":11.86939958,"remaining_time":4.895289091},
{"learn":[0.1951348522],"iteration":708,"passed_time":11.88986852,"remaining_time":4.880044767},
{"learn":[0.1949759765],"iteration":709,"passed_time":11.90560928,"remaining_time":4.862854495},
{"learn":[0.1948785989],"iteration":710,"passed_time":11.92169293,"remaining_time":4.845807674},
{"learn":[0.1947276411],"iteration":711,"passed_time":11.93657195,"remaining_time":4.828276295},
{"learn":[0.1944984716],"iteration":712,"passed_time":11.9540738,"remaining_time":4.811808106},
{"learn":[0.1943877348],"iteration":713,"passed_time":11.97679704,"remaining_time":4.797428505},
{"learn":[0.1940535359],"iteration":714,"passed_time":12.00226653,"remaining_time":4.784120223},
{"learn":[0.1939035792],"iteration":715,"passed_time":12.02144966,"remaining_time":4.768284502},
{"learn":[0.1936038793],"iteration":716,"passed_time":12.04086088,"remaining_time":4.752529469},
{"learn":[0.1933268827],"iteration":717,"passed_time":12.0523237,"remaining_time":4.733642457},
{"learn":[0.1930870371],"iteration":718,"passed_time":12.06838945,"remaining_time":4.716575013},
{"learn":[0.1929226423],"iteration":719,"passed_time":12.08856728,"remaining_time":4.701109497},
{"learn":[0.1928149928],"iteration":720,"passed_time":12.10326125,"remaining_time":4.683508862},
{"learn":[0.1925111007],"iteration":721,"passed_time":12.11788469,"remaining_time":4.665889118},
{"learn":[0.1923945382],"iteration":722,"passed_time":12.13601217,"remaining_time":4.649620155},
{"learn":[0.1920778337],"iteration":723,"passed_time":12.15432002,"remaining_time":4.633414813},
{"learn":[0.1919370821],"iteration":724,"passed_time":12.17393613,"remaining_time":4.61769991},
{"learn":[0.1917444001],"iteration":725,"passed_time":12.19137033,"remaining_time":4.601150787},
{"learn":[0.1915057656],"iteration":726,"passed_time":12.21081444,"remaining_time":4.585353977},
{"learn":[0.1912805645],"iteration":727,"passed_time":12.23102895,"remaining_time":4.569834991},
{"learn":[0.1911508087],"iteration":728,"passed_time":12.24154081,"remaining_time":4.55069624},
{"learn":[0.1909148261],"iteration":729,"passed_time":12.25642554,"remaining_time":4.533198487},
{"learn":[0.1907173473],"iteration":730,"passed_time":12.27170526,"remaining_time":4.515853236},
{"learn":[0.1905326083],"iteration":731,"passed_time":12.28714195,"remaining_time":4.498571096},
{"learn":[0.1904808525],"iteration":732,"passed_time":12.30043755,"remaining_time":4.480514086},
{"learn":[0.1903292545],"iteration":733,"passed_time":12.31882554,"remaining_time":4.464315521},
{"learn":[0.1902408436],"iteration":734,"passed_time":12.33038476,"remaining_time":4.445648927},
{"learn":[0.1901545594],"iteration":735,"passed_time":12.34405348,"remaining_time":4.427758315},
{"learn":[0.1899891055],"iteration":736,"passed_time":12.36370506,"remaining_time":4.412014153},
{"learn":[0.189839687],"iteration":737,"passed_time":12.37466624,"remaining_time":4.393174192},
{"learn":[0.1897060837],"iteration":738,"passed_time":12.39821515,"remaining_time":4.378801292},
{"learn":[0.1896065707],"iteration":739,"passed_time":12.41964156,"remaining_time":4.363657846},
{"learn":[0.1894325338],"iteration":740,"passed_time":12.43795397,"remaining_time":4.347409011},
{"learn":[0.1892697733],"iteration":741,"passed_time":12.45159727,"remaining_time":4.329531125},
{"learn":[0.1890845428],"iteration":742,"passed_time":12.46817414,"remaining_time":4.312679347},
{"learn":[0.1889791186],"iteration":743,"passed_time":12.49898931,"remaining_time":4.300727504},
{"learn":[0.1887579353],"iteration":744,"passed_time":12.51231373,"remaining_time":4.282738256},
{"learn":[0.1884917263],"iteration":745,"passed_time":12.52302381,"remaining_time":4.263871379},
{"learn":[0.1883437901],"iteration":746,"passed_time":12.53759367,"remaining_time":4.246333599},
{"learn":[0.1882225638],"iteration":747,"passed_time":12.5549909,"remaining_time":4.229756292},
{"learn":[0.1881360057],"iteration":748,"passed_time":12.56986739,"remaining_time":4.212332064},
{"learn":[0.1880163006],"iteration":749,"passed_time":12.58830009,"remaining_time":4.196100029},
{"learn":[0.1877910909],"iteration":750,"passed_time":12.60460503,"remaining_time":4.179156662},
{"learn":[0.1876186132],"iteration":751,"passed_time":12.62717637,"remaining_time":4.164281569},
{"learn":[0.1874866261],"iteration":752,"passed_time":12.64049092,"remaining_time":4.146349611},
{"learn":[0.1873509219],"iteration":753,"passed_time":12.65256414,"remaining_time":4.128024904},
{"learn":[0.1871217843],"iteration":754,"passed_time":12.66648226,"remaining_time":4.110315436},
{"learn":[0.1868699729],"iteration":755,"passed_time":12.68518767,"remaining_time":4.094161099},
{"learn":[0.1866996055],"iteration":756,"passed_time":12.70419361,"remaining_time":4.078096496},
{"learn":[0.1865086305],"iteration":757,"passed_time":12.72666652,"remaining_time":4.063131},
{"learn":[0.1862042529],"iteration":758,"passed_time":12.74230983,"remaining_time":4.045977165},
{"learn":[0.1859305734],"iteration":759,"passed_time":12.75368563,"remaining_time":4.027479673},
{"learn":[0.1857703371],"iteration":760,"passed_time":12.77288607,"remaining_time":4.011458306},
{"learn":[0.1855729559],"iteration":761,"passed_time":12.79151439,"remaining_time":3.995249902},
{"learn":[0.1854123404],"iteration":762,"passed_time":12.80395704,"remaining_time":3.977113786},
{"learn":[0.1851682361],"iteration":763,"passed_time":12.82582994,"remaining_time":3.961905583},
{"learn":[0.1850796662],"iteration":764,"passed_time":12.83537162,"remaining_time":3.942891935},
{"learn":[0.1850001423],"iteration":765,"passed_time":12.85434672,"remaining_time":3.926784769},
{"learn":[0.1848184034],"iteration":766,"passed_time":12.87534729,"remaining_time":3.911285421},
{"learn":[0.1846398383],"iteration":767,"passed_time":12.89439224,"remaining_time":3.89518099},
{"learn":[0.1844760171],"iteration":768,"passed_time":12.9112591,"remaining_time":3.878414632},
{"learn":[0.1843753267],"iteration":769,"passed_time":12.93027029,"remaining_time":3.862288527},
{"learn":[0.1841243886],"iteration":770,"passed_time":12.94701261,"remaining_time":3.845481046},
{"learn":[0.1839835333],"iteration":771,"passed_time":12.96453255,"remaining_time":3.828903395},
{"learn":[0.1837340593],"iteration":772,"passed_time":12.98045182,"remaining_time":3.811853252},
{"learn":[0.1835321672],"iteration":773,"passed_time":13.00601934,"remaining_time":3.797623218},
{"learn":[0.1831554183],"iteration":774,"passed_time":13.02259341,"remaining_time":3.780752926},
{"learn":[0.183076151],"iteration":775,"passed_time":13.05025878,"remaining_time":3.767085008},
{"learn":[0.1830590782],"iteration":776,"passed_time":13.07041734,"remaining_time":3.751226599},
{"learn":[0.1829171483],"iteration":777,"passed_time":13.08305926,"remaining_time":3.733212282},
{"learn":[0.1828105882],"iteration":778,"passed_time":13.09805776,"remaining_time":3.715880315},
{"learn":[0.1826682868],"iteration":779,"passed_time":13.12071273,"remaining_time":3.700713847},
{"learn":[0.1824983082],"iteration":780,"passed_time":13.14044592,"remaining_time":3.684708908},
{"learn":[0.1823526085],"iteration":781,"passed_time":13.16030867,"remaining_time":3.668730549},
{"learn":[0.1821625958],"iteration":782,"passed_time":13.17706481,"remaining_time":3.651881308},
{"learn":[0.1820970713],"iteration":783,"passed_time":13.19483056,"remaining_time":3.635310461},
{"learn":[0.1819802376],"iteration":784,"passed_time":13.20605639,"remaining_time":3.616945382},
{"learn":[0.1817732764],"iteration":785,"passed_time":13.22099194,"remaining_time":3.599608493},
{"learn":[0.181605809],"iteration":786,"passed_time":13.23833044,"remaining_time":3.582928059},
{"learn":[0.1814247016],"iteration":787,"passed_time":13.25349377,"remaining_time":3.56566076},
{"learn":[0.1812793923],"iteration":788,"passed_time":13.26872658,"remaining_time":3.548417375},
{"learn":[0.1811578783],"iteration":789,"passed_time":13.28120895,"remaining_time":3.530447949},
{"learn":[0.1809433465],"iteration":790,"passed_time":13.29471656,"remaining_time":3.512763288},
{"learn":[0.1808458765],"iteration":791,"passed_time":13.30835777,"remaining_time":3.495124262},
{"learn":[0.1806238933],"iteration":792,"passed_time":13.3253634,"remaining_time":3.478373547},
{"learn":[0.1804682293],"iteration":793,"passed_time":13.3420315,"remaining_time":3.46153462},
{"learn":[0.1804409329],"iteration":794,"passed_time":13.36644924,"remaining_time":3.446694458},
{"learn":[0.1804019221],"iteration":795,"passed_time":13.38502766,"remaining_time":3.430333723},
{"learn":[0.1802764889],"iteration":796,"passed_time":13.41044878,"remaining_time":3.415710292},
{"learn":[0.1800983954],"iteration":797,"passed_time":13.43420004,"remaining_time":3.400637103},
{"learn":[0.1798812626],"iteration":798,"passed_time":13.46077155,"remaining_time":3.386251668},
{"learn":[0.1797311271],"iteration":799,"passed_time":13.48288411,"remaining_time":3.370721027},
{"learn":[0.1795670926],"iteration":800,"passed_time":13.50604342,"remaining_time":3.355434009},
{"learn":[0.1794555282],"iteration":801,"passed_time":13.51976035,"remaining_time":3.337796195},
{"learn":[0.1792535842],"iteration":802,"passed_time":13.53776361,"remaining_time":3.321219715},
{"learn":[0.1791196422],"iteration":803,"passed_time":13.57171242,"remaining_time":3.308526909},
{"learn":[0.1789121023],"iteration":804,"passed_time":13.5884252,"remaining_time":3.291606104},
{"learn":[0.1786024268],"iteration":805,"passed_time":13.60317826,"remaining_time":3.274214123},
{"learn":[0.1785063156],"iteration":806,"passed_time":13.61912524,"remaining_time":3.257114215},
{"learn":[0.1782264606],"iteration":807,"passed_time":13.63149664,"remaining_time":3.239167519},
{"learn":[0.1781327301],"iteration":808,"passed_time":13.64716172,"remaining_time":3.222012223},
{"learn":[0.1779692648],"iteration":809,"passed_time":13.66884993,"remaining_time":3.20627344},
{"learn":[0.1777439826],"iteration":810,"passed_time":13.68567185,"remaining_time":3.189385918},
{"learn":[0.1775311672],"iteration":811,"passed_time":13.70242698,"remaining_time":3.172483094},
{"learn":[0.1773988199],"iteration":812,"passed_time":13.72208368,"remaining_time":3.15624803},
{"learn":[0.1772206944],"iteration":813,"passed_time":13.74786454,"remaining_time":3.141403937},
{"learn":[0.1770898276],"iteration":814,"passed_time":13.76206407,"remaining_time":3.123904114},
{"learn":[0.1770282137],"iteration":815,"passed_time":13.77794047,"remaining_time":3.106790499},
{"learn":[0.1769095072],"iteration":816,"passed_time":13.78952633,"remaining_time":3.088718872},
{"learn":[0.1767185097],"iteration":817,"passed_time":13.85239946,"remaining_time":3.082074208},
{"learn":[0.1764217546],"iteration":818,"passed_time":13.87821604,"remaining_time":3.067102689},
{"learn":[0.1761700641],"iteration":819,"passed_time":13.91508226,"remaining_time":3.054530251},
{"learn":[0.1759653411],"iteration":820,"passed_time":13.92981398,"remaining_time":3.037072718},
{"learn":[0.1757021823],"iteration":821,"passed_time":13.94983275,"remaining_time":3.020766702},
{"learn":[0.1755140674],"iteration":822,"passed_time":13.96559684,"remaining_time":3.003536623},
{"learn":[0.1754501764],"iteration":823,"passed_time":13.98073174,"remaining_time":2.986175712},
{"learn":[0.1753899818],"iteration":824,"passed_time":13.99744991,"remaining_time":2.969156042},
{"learn":[0.1752934344],"iteration":825,"passed_time":14.01142933,"remaining_time":2.951560173},
{"learn":[0.1751118752],"iteration":826,"passed_time":14.02999447,"remaining_time":2.934932339},
{"learn":[0.1749710821],"iteration":827,"passed_time":14.04569195,"remaining_time":2.917704125},
{"learn":[0.174816319],"iteration":828,"passed_time":14.06795184,"remaining_time":2.901833251},
{"learn":[0.1746253699],"iteration":829,"passed_time":14.08488109,"remaining_time":2.884855162},
{"learn":[0.1744191327],"iteration":830,"passed_time":14.099288,"remaining_time":2.867364226},
{"learn":[0.1741714754],"iteration":831,"passed_time":14.1172079,"remaining_time":2.850590056},
{"learn":[0.1740598808],"iteration":832,"passed_time":14.13053586,"remaining_time":2.832892544},
{"learn":[0.1739564296],"iteration":833,"passed_time":14.14377496,"remaining_time":2.815187822},
{"learn":[0.1738602614],"iteration":834,"passed_time":14.15721476,"remaining_time":2.797533455},
{"learn":[0.1737014418],"iteration":835,"passed_time":14.17222512,"remaining_time":2.780197272},
{"learn":[0.1734008642],"iteration":836,"passed_time":14.19078901,"remaining_time":2.763558673},
{"learn":[0.1731559548],"iteration":837,"passed_time":14.20726376,"remaining_time":2.74651161},
{"learn":[0.1730214591],"iteration":838,"passed_time":14.22192133,"remaining_time":2.729117203},
{"learn":[0.172884872],"iteration":839,"passed_time":14.23969464,"remaining_time":2.712322788},
{"learn":[0.1727506639],"iteration":840,"passed_time":14.25716802,"remaining_time":2.695469341},
{"learn":[0.172620661],"iteration":841,"passed_time":14.26899958,"remaining_time":2.677555741},
{"learn":[0.1724670408],"iteration":842,"passed_time":14.29108377,"remaining_time":2.661566017},
{"learn":[0.1724241998],"iteration":843,"passed_time":14.30487141,"remaining_time":2.644028364},
{"learn":[0.1723653259],"iteration":844,"passed_time":14.32062228,"remaining_time":2.626859707},
{"learn":[0.1721481664],"iteration":845,"passed_time":14.33216649,"remaining_time":2.608928653},
{"learn":[0.1719530121],"iteration":846,"passed_time":14.35215405,"remaining_time":2.592537863},
{"learn":[0.1717870391],"iteration":847,"passed_time":14.37703524,"remaining_time":2.577015751},
{"learn":[0.1716532198],"iteration":848,"passed_time":14.39862746,"remaining_time":2.560886626},
{"learn":[0.1714559526],"iteration":849,"passed_time":14.41344407,"remaining_time":2.543548954},
{"learn":[0.1713029509],"iteration":850,"passed_time":14.43532404,"remaining_time":2.527453915},
{"learn":[0.17110192],"iteration":851,"passed_time":14.45212439,"remaining_time":2.510462922},
{"learn":[0.171007679],"iteration":852,"passed_time":14.47164884,"remaining_time":2.493941829},
{"learn":[0.170822502],"iteration":853,"passed_time":14.48823977,"remaining_time":2.476912186},
{"learn":[0.1707118154],"iteration":854,"passed_time":14.51322486,"remaining_time":2.461307141},
{"learn":[0.17057018],"iteration":855,"passed_time":14.52987203,"remaining_time":2.444277537},
{"learn":[0.1704207451],"iteration":856,"passed_time":14.54611054,"remaining_time":2.427180639},
{"learn":[0.1702841797],"iteration":857,"passed_time":14.5662711,"remaining_time":2.410734844},
{"learn":[0.1699694689],"iteration":858,"passed_time":14.58110473,"remaining_time":2.393406014},
{"learn":[0.1698624198],"iteration":859,"passed_time":14.59406214,"remaining_time":2.375777558},
{"learn":[0.1697150668],"iteration":860,"passed_time":14.6106129,"remaining_time":2.358740061},
{"learn":[0.1695887619],"iteration":861,"passed_time":14.62531012,"remaining_time":2.341406957},
{"learn":[0.1694587417],"iteration":862,"passed_time":14.63999533,"remaining_time":2.324078053},
{"learn":[0.1693198733],"iteration":863,"passed_time":14.65578159,"remaining_time":2.306928584},
{"learn":[0.1691945627],"iteration":864,"passed_time":14.66942827,"remaining_time":2.289448342},
{"learn":[0.1691128663],"iteration":865,"passed_time":14.68508234,"remaining_time":2.272287568},
{"learn":[0.1689990215],"iteration":866,"passed_time":14.70243432,"remaining_time":2.255390732},
{"learn":[0.168876971],"iteration":867,"passed_time":14.72356498,"remaining_time":2.239067485},
{"learn":[0.168745332],"iteration":868,"passed_time":14.73747671,"remaining_time":2.221644936},
{"learn":[0.1686706353],"iteration":869,"passed_time":14.75180203,"remaining_time":2.204292257},
{"learn":[0.1685237556],"iteration":870,"passed_time":14.7643059,"remaining_time":2.186676764},
{"learn":[0.1681810851],"iteration":871,"passed_time":14.78241126,"remaining_time":2.16989523},
{"learn":[0.1680825845],"iteration":872,"passed_time":14.79383231,"remaining_time":2.152138262},
{"learn":[0.1679491582],"iteration":873,"passed_time":14.81437095,"remaining_time":2.135710228},
{"learn":[0.1675841895],"iteration":874,"passed_time":14.8258695,"remaining_time":2.117981357},
{"learn":[0.1674297642],"iteration":875,"passed_time":14.84091904,"remaining_time":2.100769362},
{"learn":[0.1672554025],"iteration":876,"passed_time":14.85621503,"remaining_time":2.083596862},
{"learn":[0.1670977741],"iteration":877,"passed_time":14.87989906,"remaining_time":2.067594175},
{"learn":[0.1668456344],"iteration":878,"passed_time":14.89110609,"remaining_time":2.04985647},
{"learn":[0.1666717719],"iteration":879,"passed_time":14.90536123,"remaining_time":2.032549259},
{"learn":[0.1665840313],"iteration":880,"passed_time":14.91755978,"remaining_time":2.014971185},
{"learn":[0.1664317216],"iteration":881,"passed_time":14.93558428,"remaining_time":1.998184744},
{"learn":[0.1661472001],"iteration":882,"passed_time":14.95114151,"remaining_time":1.981068581},
{"learn":[0.1660531604],"iteration":883,"passed_time":14.96066693,"remaining_time":1.963164439},
{"learn":[0.1659212372],"iteration":884,"passed_time":14.96933997,"remaining_time":1.945168471},
{"learn":[0.1657241799],"iteration":885,"passed_time":14.97785211,"remaining_time":1.927172844},
{"learn":[0.165503203],"iteration":886,"passed_time":14.98854038,"remaining_time":1.909475832},
{"learn":[0.1653868582],"iteration":887,"passed_time":14.99640503,"remaining_time":1.891438472},
{"learn":[0.1650702824],"iteration":888,"passed_time":15.00267526,"remaining_time":1.873224919},
{"learn":[0.1650401371],"iteration":889,"passed_time":15.01175108,"remaining_time":1.855384965},
{"learn":[0.1649484842],"iteration":890,"passed_time":15.018187,"remaining_time":1.837241731},
{"learn":[0.1647442337],"iteration":891,"passed_time":15.02642181,"remaining_time":1.819342551},
{"learn":[0.1644404842],"iteration":892,"passed_time":15.03306347,"remaining_time":1.801274122},
{"learn":[0.164387753],"iteration":893,"passed_time":15.04018249,"remaining_time":1.783287857}
]}